helloapp/__init__.py
helloapp/hello.py
myapp/__init__.py
myapp/myapplication.py
setuptls-2.0.dist-info/METADATA
setuptls-2.0.dist-info/WHEEL
setuptls-2.0.dist-info/top_level.txt
setuptls-2.0.dist-info/RECORD
