Metadata-Version: 2.1
Name: setuptls
Version: 2.0
Summary: Test Hello
Home-page: UNKNOWN
Author: lhb
Author-email: 1850801419@qq.com
License: MIT
Platform: UNKNOWN
